macry/__init__.py
macry/builder.py
macry/fields.py
macry/connects/__init__.py
macry/connects/firestore_connect.py
macry-0.0.3.dist-info/LICENSE
macry-0.0.3.dist-info/WHEEL
macry-0.0.3.dist-info/METADATA
macry-0.0.3.dist-info/RECORD
